nlptklzxcvd/__init__.py
nlptklzxcvd/loader.py
nlptklzxcvd/data/lemmatization.txt
nlptklzxcvd/data/ner.txt
nlptklzxcvd/data/pos_tagging.txt
nlptklzxcvd/data/sample1.txt
nlptklzxcvd/data/stemming.txt
nlptklzxcvd/data/stopwords.txt
nlptklzxcvd/data/streamlitx.txt
nlptklzxcvd/data/streamlitz.txt
nlptklzxcvd/data/tokenization.txt
nlptklzxcvd-0.1.2.dist-info/LICENSE
nlptklzxcvd-0.1.2.dist-info/METADATA
nlptklzxcvd-0.1.2.dist-info/WHEEL
nlptklzxcvd-0.1.2.dist-info/top_level.txt
nlptklzxcvd-0.1.2.dist-info/RECORD
