Metadata-Version: 2.1
Name: nlptklzxcvd
Version: 0.1.2
Summary: A simple library
Author-email: Your Name <your@email.com>
License: MIT
Requires-Python: >=3.8
License-File: LICENSE
